wenku_dl/__init__.py
wenku_dl/__main__.py
wenku_dl/download.py
wenku_dl/wenku.py
wenku_dl-2019.4.28.4.dist-info/METADATA
wenku_dl-2019.4.28.4.dist-info/WHEEL
wenku_dl-2019.4.28.4.dist-info/entry_points.txt
wenku_dl-2019.4.28.4.dist-info/top_level.txt
wenku_dl-2019.4.28.4.dist-info/RECORD
